{"116827562":{"displayProperties":{"description":"Добро пожаловать в закрытые матчи \"Хаос\", где все высосано из пальца, а набор очков лишен смысла.","name":"Закрытые матчи: \"Хаос\"","icon":"/common/destiny2_content/icons/DestinyActivityModeDefinition_52f64830161b33289d36edc03f6d2ea6.png","hasIcon":true},"pgcrImage":"/img/theme/destiny/bgs/stats/banner_crucible_1.jpg","modeType":56,"activityModeCategory":2,"isTeamBased":true,"tier":0,"isAggregateMode":false,"parentHashes":[1164760504],"friendlyName":"private-matches-mayhem","supportsFeedFiltering":false,"display":false,"order":1905,"hash":116827562,"index":45,"redacted":false,"blacklisted":false},"122250361":{"displayProperties":{"description":"Добро пожаловать в закрытые матчи, где все высосано из пальца, а набор очков лишен смысла.","name":"Закрытые матчи","icon":"/common/destiny2_content/icons/DestinyActivityModeDefinition_fb3e9149c43f7a2e8f8b66cbea7845fe.png","hasIcon":true},"pgcrImage":"/img/theme/destiny/bgs/stats/banner_crucible_1.jpg","modeType":32,"activityModeCategory":2,"isTeamBased":false,"tier":0,"isAggregateMode":true,"friendlyName":"private-matches","supportsFeedFiltering":false,"activityModeMappings":{"29726492":56,"1218001922":53,"1859507212":52,"2491884566":57,"2903879783":55,"3767360267":54,"4242525388":51},"display":true,"order":1899,"hash":122250361,"index":39,"redacted":false,"blacklisted":false},"152599670":{"displayProperties":{"description":"Добро пожаловать в закрытые матчи \"Обратный отсчет\", где все высосано из пальца, а набор очков лишен смысла.","name":"Закрытые матчи: \"Обратный отсчет\"","icon":"/common/destiny2_content/icons/DestinyActivityModeDefinition_fb3e9149c43f7a2e8f8b66cbea7845fe.png","hasIcon":true},"pgcrImage":"/img/theme/destiny/bgs/stats/banner_crucible_1.jpg","modeType":54,"activityModeCategory":2,"isTeamBased":true,"tier":0,"isAggregateMode":false,"parentHashes":[1164760504],"friendlyName":"private-matches-countdown","supportsFeedFiltering":false,"display":false,"order":1902,"hash":152599670,"index":42,"redacted":false,"blacklisted":false},"157639802":{"displayProperties":{"description":"Каждый за себя.","name":"Стычка","icon":"/common/destiny2_content/icons/DestinyActivityModeDefinition_5b371fef4ecafe733ad487a8fae3b9f5.png","hasIcon":true},"pgcrImage":"/img/theme/destiny/bgs/stats/banner_crucible_1.jpg","modeType":48,"activityModeCategory":2,"isTeamBased":false,"tier":0,"isAggregateMode":false,"parentHashes":[1164760504],"friendlyName":"rumble","supportsFeedFiltering":false,"display":true,"order":1377,"hash":157639802,"index":38,"redacted":false,"blacklisted":false},"175275639":{"displayProperties":{"description":"Чуть более героическое, чем наведение порядка в ящике для носков.","name":"Героическое приключение","icon":"/common/destiny2_content/icons/DestinyActivityModeDefinition_abf5e799b91b9a4dea7f8a7e00106d41.png","hasIcon":true},"pgcrImage":"/img/theme/destiny/bgs/stats/banner_story_1.jpg","modeType":58,"activityModeCategory":1,"isTeamBased":false,"tier":0,"isAggregateMode":false,"parentHashes":[1164760493],"friendlyName":"heroicAdventure","supportsFeedFiltering":false,"display":true,"order":3310,"hash":175275639,"index":47,"redacted":false,"blacklisted":false},"244324567":{"displayProperties":{"description":"Статистика по \"Столкновению\" в быстрой игре.","name":"Столкновение: быстрая игра","icon":"/common/destiny2_content/icons/DestinyActivityModeDefinition_fb3e9149c43f7a2e8f8b66cbea7845fe.png","hasIcon":true},"pgcrImage":"/img/theme/destiny/bgs/stats/banner_crucible_1.jpg","modeType":71,"activityModeCategory":2,"isTeamBased":true,"tier":0,"isAggregateMode":false,"parentHashes":[1585787840],"friendlyName":"clashQuickplay","supportsFeedFiltering":false,"display":true,"order":1100,"hash":244324567,"index":20,"redacted":false,"blacklisted":false},"470484296":{"displayProperties":{"description":"Статистика по режиму Испытаний Девяти: \"Выживание\"","name":"Испытания Девяти: Выживание","icon":"/common/destiny2_content/icons/DestinyActivityModeDefinition_f4b12d402bb36270cd911f4e1fa8bb0c.png","hasIcon":true},"pgcrImage":"/img/theme/destiny/bgs/stats/banner_crucible_1.jpg","modeType":42,"activityModeCategory":2,"isTeamBased":true,"tier":0,"isAggregateMode":false,"parentHashes":[1370326378],"friendlyName":"trialsSurvival","supportsFeedFiltering":false,"display":true,"order":1377,"hash":470484296,"index":32,"redacted":false,"blacklisted":false},"532484583":{"displayProperties":{"description":"Трудности, с которыми сталкиваются Стражи во время престижных Сумрачных налетов, — дело рук самих Стражей.","name":"Сумрачные налеты \"Престиж\" с подсчетом очков","icon":"/common/destiny2_content/icons/DestinyActivityModeDefinition_abf5e799b91b9a4dea7f8a7e00106d41.png","hasIcon":true},"pgcrImage":"/img/theme/destiny/bgs/stats/banner_strikes_1.jpg","modeType":47,"activityModeCategory":1,"isTeamBased":false,"tier":0,"isAggregateMode":false,"parentHashes":[2394616003],"friendlyName":"scored_heroicNightfall","supportsFeedFiltering":false,"display":true,"order":3310,"hash":532484583,"index":13,"redacted":false,"blacklisted":false},"547513715":{"displayProperties":{"description":"Сколько раз нас вынесли всей командой в сумрачном налете на прошлой неделе, пока мы пытались установить новый рекорд? (Намек: не больше одного раза)","name":"Сумрачные налеты с подсчетом очков","icon":"/common/destiny2_content/icons/DestinyActivityModeDefinition_234e7e18549d5eae2ddb012f2bcb203a.png","hasIcon":true},"pgcrImage":"/img/theme/destiny/bgs/stats/banner_strikes_1.jpg","modeType":46,"activityModeCategory":1,"isTeamBased":false,"tier":0,"isAggregateMode":false,"parentHashes":[2394616003],"friendlyName":"scored_nightfall","supportsFeedFiltering":false,"display":true,"order":3210,"hash":547513715,"index":12,"redacted":false,"blacklisted":false},"575409284":{"displayProperties":{"description":"Добро пожаловать в закрытые матчи \"Столкновение\", где все высосано из пальца, а набор очков лишен смысла.","name":"Закрытые матчи: \"Столкновение\"","icon":"/common/destiny2_content/icons/DestinyActivityModeDefinition_cf348b63307220263eff699dc56bd081.png","hasIcon":true},"pgcrImage":"/img/theme/destiny/bgs/stats/banner_crucible_1.jpg","modeType":51,"activityModeCategory":2,"isTeamBased":true,"tier":0,"isAggregateMode":false,"parentHashes":[1164760504],"friendlyName":"private-matches-clash","supportsFeedFiltering":false,"display":false,"order":1900,"hash":575409284,"index":40,"redacted":false,"blacklisted":false},"748895195":{"displayProperties":{"description":"Все игровые режимы в одном флаконе.","name":"Все","icon":"/common/destiny2_content/icons/DestinyActivityModeDefinition_f6de6d95f600f199c9a674c73cbefbcc.png","hasIcon":true},"pgcrImage":"/img/theme/destiny/bgs/stats/banner_allmodes.jpg","modeType":0,"activityModeCategory":0,"isTeamBased":false,"tier":0,"isAggregateMode":true,"friendlyName":"all","supportsFeedFiltering":false,"display":true,"order":0,"hash":748895195,"index":0,"redacted":false,"blacklisted":false},"803838459":{"displayProperties":{"description":"Статистика по заданиям в кузницах \"Черного арсенала\".","name":"Кузница","icon":"/common/destiny2_content/icons/DestinyActivityModeDefinition_d08435f6d51f7ff593c92e7f1394e933.png","hasIcon":true},"pgcrImage":"/img/theme/destiny/bgs/stats/banner_strikes_1.jpg","modeType":66,"activityModeCategory":1,"isTeamBased":false,"tier":0,"isAggregateMode":false,"parentHashes":[1164760493],"friendlyName":"blackArmoryRun","supportsFeedFiltering":false,"display":true,"order":3300,"hash":803838459,"index":56,"redacted":false,"blacklisted":false},"910991990":{"displayProperties":{"description":"Из убитых Стражей выпадают гербы. Собирайте их, чтобы победить.","name":"Превосходство","icon":"/common/destiny2_content/icons/DestinyActivityModeDefinition_ca750af7ed2f0ec3c8e2f019c85f7bab.png","hasIcon":true},"pgcrImage":"/img/theme/destiny/bgs/stats/banner_crucible_1.jpg","modeType":31,"activityModeCategory":2,"isTeamBased":true,"tier":0,"isAggregateMode":false,"parentHashes":[1164760504],"friendlyName":"supremacy","supportsFeedFiltering":false,"display":true,"order":1400,"hash":910991990,"index":25,"redacted":false,"blacklisted":false},"946648766":{"displayProperties":{"description":"Статистика по режиму \"Багряные дни\" в Горниле.","name":"Багряные дни ","icon":"/common/destiny2_content/icons/DestinyActivityModeDefinition_f9d1438e0536f36e868e691eb0acfc4d.png","hasIcon":true},"pgcrImage":"/img/theme/destiny/bgs/stats/banner_crucible_1.jpg","modeType":15,"activityModeCategory":2,"isTeamBased":true,"tier":0,"isAggregateMode":false,"parentHashes":[1703282980],"friendlyName":"crimsonDoubles","supportsFeedFiltering":false,"display":true,"order":1377,"hash":946648766,"index":36,"redacted":false,"blacklisted":false},"1164760493":{"displayProperties":{"description":"Все для тех, кто обожает расстреливать инопланетян.","name":"PvE","icon":"/common/destiny2_content/icons/DestinyActivityModeDefinition_5f8a923a0d0ac1e4289ae3be03f94aa2.png","hasIcon":true},"pgcrImage":"/img/theme/destiny/bgs/stats/banner_story_1.jpg","modeType":7,"activityModeCategory":1,"isTeamBased":false,"tier":0,"isAggregateMode":true,"friendlyName":"pve","supportsFeedFiltering":false,"display":true,"order":99999,"hash":1164760493,"index":1,"redacted":false,"blacklisted":false},"1164760504":{"displayProperties":{"description":"Вся ваша статистика из Горнила.","name":"Горнило","icon":"/common/destiny2_content/icons/DestinyActivityModeDefinition_fb3e9149c43f7a2e8f8b66cbea7845fe.png","hasIcon":true},"pgcrImage":"/img/theme/destiny/bgs/stats/banner_crucible_1.jpg","modeType":5,"activityModeCategory":2,"isTeamBased":false,"tier":0,"isAggregateMode":true,"friendlyName":"crucible","supportsFeedFiltering":false,"display":true,"order":1000,"hash":1164760504,"index":4,"redacted":false,"blacklisted":false},"1264443021":{"displayProperties":{"description":"Статистика по всем вариантам \"Хаоса\" в Горниле.","name":"Хаос","icon":"/common/destiny2_content/icons/DestinyActivityModeDefinition_fb3e9149c43f7a2e8f8b66cbea7845fe.png","hasIcon":true},"pgcrImage":"/img/theme/destiny/bgs/stats/banner_crucible_1.jpg","modeType":25,"activityModeCategory":2,"isTeamBased":true,"tier":0,"isAggregateMode":false,"parentHashes":[1164760504],"friendlyName":"allMayhem","supportsFeedFiltering":false,"display":true,"order":1377,"hash":1264443021,"index":37,"redacted":false,"blacklisted":false},"1317961215":{"displayProperties":{"description":"Статистика по режиму \"Спасение\" в Железном знамени.","name":"Железное Знамя: Спасение","icon":"/common/destiny2_content/icons/DestinyActivityModeDefinition_fe57052d7cf971f7502daa75a2ca2437.png","hasIcon":true},"pgcrImage":"/img/theme/destiny/bgs/stats/banner_crucible_1.jpg","modeType":68,"activityModeCategory":2,"isTeamBased":true,"tier":0,"isAggregateMode":false,"parentHashes":[1826469369],"friendlyName":"iron-banner-salvage","supportsFeedFiltering":false,"display":true,"order":1400,"hash":1317961215,"index":29,"redacted":false,"blacklisted":false},"1340118533":{"displayProperties":{"description":"Статистика по \"Контролю\" в состязательном режиме.","name":"Контроль: состязательная игра","icon":"/common/destiny2_content/icons/DestinyActivityModeDefinition_922ae83203f6134bae00937d12eab3a2.png","hasIcon":true},"pgcrImage":"/img/theme/destiny/bgs/stats/banner_crucible_1.jpg","modeType":74,"activityModeCategory":2,"isTeamBased":true,"tier":0,"isAggregateMode":false,"parentHashes":[3199098480],"friendlyName":"controlCompetitive","supportsFeedFiltering":false,"display":true,"order":1150,"hash":1340118533,"index":18,"redacted":false,"blacklisted":false},"1350109474":{"displayProperties":{"description":"Статистика по Сумрачным налетам на уровне \"Престиж\"","name":"Сумрачные налеты \"Престиж\"","icon":"/common/destiny2_content/icons/DestinyActivityModeDefinition_abf5e799b91b9a4dea7f8a7e00106d41.png","hasIcon":true},"pgcrImage":"/img/theme/destiny/bgs/stats/banner_strikes_1.jpg","modeType":17,"activityModeCategory":1,"isTeamBased":false,"tier":0,"isAggregateMode":false,"parentHashes":[2394616003],"friendlyName":"heroicNightfall","supportsFeedFiltering":false,"display":true,"order":3300,"hash":1350109474,"index":11,"redacted":false,"blacklisted":false},"1370326378":{"displayProperties":{"description":"Статистика по Испытаниям Девяти","name":"Испытания Девяти","icon":"/common/destiny2_content/icons/DestinyActivityModeDefinition_f4b12d402bb36270cd911f4e1fa8bb0c.png","hasIcon":true},"pgcrImage":"/img/theme/destiny/bgs/stats/banner_crucible_1.jpg","modeType":39,"activityModeCategory":2,"isTeamBased":false,"tier":0,"isAggregateMode":true,"parentHashes":[1164760504],"friendlyName":"trialsofthenine","supportsFeedFiltering":false,"display":true,"order":1377,"hash":1370326378,"index":30,"redacted":false,"blacklisted":false},"1372032677":{"displayProperties":{"description":"Эта команда настолько горяча, что хочется поставить ей \"лайк\" и подписаться на обновления.","name":"Команда \"Ожог\"","icon":"/common/destiny2_content/icons/DestinyActivityModeDefinition_fb3e9149c43f7a2e8f8b66cbea7845fe.png","hasIcon":true},"pgcrImage":"/img/theme/destiny/bgs/stats/banner_crucible_1.jpg","modeType":62,"activityModeCategory":2,"isTeamBased":true,"tier":0,"isAggregateMode":false,"parentHashes":[1164760504],"friendlyName":"scorchedTeam","supportsFeedFiltering":false,"display":true,"order":5000,"hash":1372032677,"index":51,"redacted":false,"blacklisted":false},"1418469392":{"displayProperties":{"description":"Убивайте врагов, вносите частицы в банк и не дайте соперникам выиграть.","name":"Гамбит Прайм","icon":"/common/destiny2_content/icons/DestinyActivityModeDefinition_1e392d102336226d85cc12bc5dbe1ff0.png","hasIcon":true},"pgcrImage":"/img/theme/destiny/bgs/stats/banner_crucible_1.jpg","modeType":75,"activityModeCategory":3,"isTeamBased":true,"tier":0,"isAggregateMode":false,"parentHashes":[2449176354],"friendlyName":"gambit-prime","supportsFeedFiltering":false,"display":true,"order":5000,"hash":1418469392,"index":53,"redacted":false,"blacklisted":false},"1505888634":{"displayProperties":{"description":"Статистика по режиму \"Обратный отсчет\" в Горниле","name":"Обратный отсчет","icon":"/common/destiny2_content/icons/DestinyActivityModeDefinition_fb3e9149c43f7a2e8f8b66cbea7845fe.png","hasIcon":true},"pgcrImage":"/img/theme/destiny/bgs/stats/banner_crucible_1.jpg","modeType":38,"activityModeCategory":2,"isTeamBased":true,"tier":0,"isAggregateMode":false,"parentHashes":[1164760504],"friendlyName":"countdown","supportsFeedFiltering":false,"display":true,"order":1377,"hash":1505888634,"index":24,"redacted":false,"blacklisted":false},"1585787840":{"displayProperties":{"description":"Статистика по режиму \"Столкновение\" в Горниле","name":"Столкновение","icon":"/common/destiny2_content/icons/DestinyActivityModeDefinition_fb3e9149c43f7a2e8f8b66cbea7845fe.png","hasIcon":true},"pgcrImage":"/img/theme/destiny/bgs/stats/banner_crucible_1.jpg","modeType":12,"activityModeCategory":2,"isTeamBased":true,"tier":0,"isAggregateMode":true,"parentHashes":[1164760504],"friendlyName":"clash","supportsFeedFiltering":false,"display":true,"order":1100,"hash":1585787840,"index":19,"redacted":false,"blacklisted":false},"1589650888":{"displayProperties":{"description":"","name":"Общение","icon":"/common/destiny2_content/icons/DestinyActivityModeDefinition_f6de6d95f600f199c9a674c73cbefbcc.png","hasIcon":true},"pgcrImage":"/img/theme/destiny/bgs/stats/banner_crucible_1.jpg","modeType":40,"activityModeCategory":0,"isTeamBased":false,"tier":0,"isAggregateMode":false,"parentHashes":[],"friendlyName":"social","supportsFeedFiltering":false,"display":false,"order":1377,"hash":1589650888,"index":33,"redacted":false,"blacklisted":false},"1668923154":{"displayProperties":{"description":"Горячее, чем плавящийся под июльским солнцем асфальт в Аризоне.","name":"Ожог","icon":"/common/destiny2_content/icons/DestinyActivityModeDefinition_fb3e9149c43f7a2e8f8b66cbea7845fe.png","hasIcon":true},"pgcrImage":"/img/theme/destiny/bgs/stats/banner_crucible_1.jpg","modeType":61,"activityModeCategory":2,"isTeamBased":true,"tier":0,"isAggregateMode":false,"parentHashes":[1164760504],"friendlyName":"scorched","supportsFeedFiltering":false,"display":true,"order":5000,"hash":1668923154,"index":50,"redacted":false,"blacklisted":false},"1686739444":{"displayProperties":{"description":"Сколько вексов я пришиб до того, как они успели все объяснить?","name":"Сюжет","icon":"/common/destiny2_content/icons/DestinyActivityModeDefinition_5f8a923a0d0ac1e4289ae3be03f94aa2.png","hasIcon":true},"pgcrImage":"/img/theme/destiny/bgs/stats/banner_story_1.jpg","modeType":2,"activityModeCategory":1,"isTeamBased":false,"tier":0,"isAggregateMode":false,"parentHashes":[1164760493],"friendlyName":"story","supportsFeedFiltering":false,"display":true,"order":4000,"hash":1686739444,"index":8,"redacted":false,"blacklisted":false},"1703282980":{"displayProperties":{"description":"Коллекция всех матчей \"Напарники\".","name":"Все \"Напарники\"","icon":"/common/destiny2_content/icons/DestinyActivityModeDefinition_f9d1438e0536f36e868e691eb0acfc4d.png","hasIcon":true},"pgcrImage":"/img/theme/destiny/bgs/stats/banner_crucible_1.jpg","modeType":49,"activityModeCategory":2,"isTeamBased":true,"tier":0,"isAggregateMode":true,"parentHashes":[1164760504],"friendlyName":"allDoubles","supportsFeedFiltering":false,"display":true,"order":1377,"hash":1703282980,"index":34,"redacted":false,"blacklisted":false},"1826469369":{"displayProperties":{"description":"Даже самое острое железное копье может притупиться со временем.","name":"Железное знамя","icon":"/common/destiny2_content/icons/DestinyActivityModeDefinition_fe57052d7cf971f7502daa75a2ca2437.png","hasIcon":true},"pgcrImage":"/img/theme/destiny/bgs/stats/banner_crucible_1.jpg","modeType":19,"activityModeCategory":2,"isTeamBased":false,"tier":0,"isAggregateMode":true,"parentHashes":[1164760504],"friendlyName":"iron-banner","supportsFeedFiltering":false,"display":true,"order":1020,"hash":1826469369,"index":15,"redacted":false,"blacklisted":false},"1848252830":{"displayProperties":{"description":"Убивайте врагов, вносите частицы в банк и не дайте соперникам выиграть.","name":"Гамбит","icon":"/common/destiny2_content/icons/DestinyActivityModeDefinition_96f7e9009d4f26e30cfd60564021925e.png","hasIcon":true},"pgcrImage":"/img/theme/destiny/bgs/stats/banner_crucible_1.jpg","modeType":63,"activityModeCategory":3,"isTeamBased":true,"tier":0,"isAggregateMode":false,"parentHashes":[2449176354],"friendlyName":"pvecomp_gambit","supportsFeedFiltering":false,"display":true,"order":5000,"hash":1848252830,"index":52,"redacted":false,"blacklisted":false},"2043403989":{"displayProperties":{"description":"Вся ваша статистика по рейдам.","name":"Рейды","icon":"/common/destiny2_content/icons/DestinyActivityModeDefinition_bfe80e3dafe6686a9dc42df0606bdc9b.png","hasIcon":true},"pgcrImage":"/img/theme/destiny/bgs/stats/banner_raid_1.jpg","modeType":4,"activityModeCategory":1,"isTeamBased":false,"tier":0,"isAggregateMode":false,"parentHashes":[1164760493],"friendlyName":"raid","supportsFeedFiltering":false,"display":true,"order":2000,"hash":2043403989,"index":7,"redacted":false,"blacklisted":false},"2096553452":{"displayProperties":{"description":"Статистика по режиму \"Спасение\" в Горниле.","name":"Спасение","icon":"/common/destiny2_content/icons/DestinyActivityModeDefinition_fb3e9149c43f7a2e8f8b66cbea7845fe.png","hasIcon":true},"pgcrImage":"/img/theme/destiny/bgs/stats/banner_crucible_1.jpg","modeType":60,"activityModeCategory":2,"isTeamBased":true,"tier":0,"isAggregateMode":false,"parentHashes":[1164760504],"friendlyName":"lockdown","supportsFeedFiltering":false,"display":true,"order":5000,"hash":2096553452,"index":49,"redacted":false,"blacklisted":false},"-2055718213":{"displayProperties":{"description":"Статистика по режиму \"Выживание\" в Горниле","name":"Выживание","icon":"/common/destiny2_content/icons/DestinyActivityModeDefinition_fb3e9149c43f7a2e8f8b66cbea7845fe.png","hasIcon":true},"pgcrImage":"/img/theme/destiny/bgs/stats/banner_crucible_1.jpg","modeType":37,"activityModeCategory":2,"isTeamBased":true,"tier":0,"isAggregateMode":false,"parentHashes":[1164760504],"friendlyName":"survival","supportsFeedFiltering":false,"display":true,"order":1376,"hash":2239249083,"index":23,"redacted":false,"blacklisted":false},"-2031201205":{"displayProperties":{"description":"Статистика по режиму Испытаний Девяти: \"Обратный отсчет\"","name":"Испытания Девяти: Обратный отсчет","icon":"/common/destiny2_content/icons/DestinyActivityModeDefinition_f4b12d402bb36270cd911f4e1fa8bb0c.png","hasIcon":true},"pgcrImage":"/img/theme/destiny/bgs/stats/banner_crucible_1.jpg","modeType":41,"activityModeCategory":2,"isTeamBased":true,"tier":0,"isAggregateMode":false,"parentHashes":[1370326378],"friendlyName":"trialsCountdown","supportsFeedFiltering":false,"display":true,"order":1377,"hash":2263766091,"index":31,"redacted":false,"blacklisted":false},"-1900351293":{"displayProperties":{"description":"Сводная статистика по обычным и особым налетам (например, сумрачным и героическим налетам).","name":"Налеты","icon":"/common/destiny2_content/icons/DestinyActivityModeDefinition_38e26baf417d26bb3548d97bf4872b54.png","hasIcon":true},"pgcrImage":"/img/theme/destiny/bgs/stats/banner_strikes_1.jpg","modeType":18,"activityModeCategory":1,"isTeamBased":false,"tier":0,"isAggregateMode":true,"parentHashes":[1164760493],"friendlyName":"strikes","supportsFeedFiltering":false,"display":true,"order":3100,"hash":2394616003,"index":14,"redacted":false,"blacklisted":false},"-1845790942":{"displayProperties":{"description":"Категория, в которой собраны все режимы, где вы сражаетесь с персонажами и другими игроками.","name":"Совместно-состязательный режим","icon":"/common/destiny2_content/icons/DestinyActivityModeDefinition_5f8a923a0d0ac1e4289ae3be03f94aa2.png","hasIcon":true},"pgcrImage":"/img/theme/destiny/bgs/stats/banner_story_1.jpg","modeType":64,"activityModeCategory":3,"isTeamBased":false,"tier":0,"isAggregateMode":true,"friendlyName":"pveCompetitive","supportsFeedFiltering":false,"display":true,"order":99999,"hash":2449176354,"index":2,"redacted":false,"blacklisted":false},"-1808243978":{"displayProperties":{"description":"Статистика по заданиям состязательного режима.","name":"Состязательная игра. PvP","icon":"/common/destiny2_content/icons/DestinyActivityModeDefinition_fb3e9149c43f7a2e8f8b66cbea7845fe.png","hasIcon":true},"pgcrImage":"/img/theme/destiny/bgs/stats/banner_crucible_1.jpg","modeType":69,"activityModeCategory":2,"isTeamBased":false,"tier":0,"isAggregateMode":true,"friendlyName":"pvpCompetitive","supportsFeedFiltering":false,"display":true,"order":1000,"hash":2486723318,"index":5,"redacted":false,"blacklisted":false},"-1748182994":{"displayProperties":{"description":"","name":"Поединок","icon":"/common/destiny2_content/icons/DestinyActivityModeDefinition_fb3e9149c43f7a2e8f8b66cbea7845fe.png","hasIcon":true},"pgcrImage":"/img/theme/destiny/bgs/stats/banner_crucible_1.jpg","modeType":59,"activityModeCategory":2,"isTeamBased":true,"tier":0,"isAggregateMode":false,"parentHashes":[1164760504],"friendlyName":"showdown","supportsFeedFiltering":false,"display":true,"order":5000,"hash":2546784302,"index":48,"redacted":false,"blacklisted":false},"-1741423138":{"displayProperties":{"description":"Добро пожаловать в закрытые матчи \"Стычка\", где все высосано из пальца, а набор очков лишен смысла.","name":"Закрытые матчи: \"Стычка\"","icon":"/common/destiny2_content/icons/DestinyActivityModeDefinition_5b371fef4ecafe733ad487a8fae3b9f5.png","hasIcon":true},"pgcrImage":"/img/theme/destiny/bgs/stats/banner_crucible_1.jpg","modeType":57,"activityModeCategory":2,"isTeamBased":false,"tier":0,"isAggregateMode":false,"parentHashes":[1164760504],"friendlyName":"private-matches-rumble","supportsFeedFiltering":false,"display":false,"order":1906,"hash":2553544158,"index":46,"redacted":false,"blacklisted":false},"-1451282428":{"displayProperties":{"description":"Статистика по режиму Железного знамени: \"Контроль\"","name":"Железное знамя: Контроль","icon":"/common/destiny2_content/icons/DestinyActivityModeDefinition_fe57052d7cf971f7502daa75a2ca2437.png","hasIcon":true},"pgcrImage":"/img/theme/destiny/bgs/stats/banner_crucible_1.jpg","modeType":43,"activityModeCategory":2,"isTeamBased":true,"tier":0,"isAggregateMode":false,"parentHashes":[1826469369],"friendlyName":"iron-banner-control","supportsFeedFiltering":false,"display":true,"order":1400,"hash":2843684868,"index":28,"redacted":false,"blacklisted":false},"-1270265980":{"displayProperties":{"description":"Добро пожаловать в закрытые матчи \"Контроль\", где все высосано из пальца, а набор очков лишен смысла.","name":"Закрытые матчи: \"Контроль\"","icon":"/common/destiny2_content/icons/DestinyActivityModeDefinition_922ae83203f6134bae00937d12eab3a2.png","hasIcon":true},"pgcrImage":"/img/theme/destiny/bgs/stats/banner_crucible_1.jpg","modeType":52,"activityModeCategory":2,"isTeamBased":true,"tier":0,"isAggregateMode":false,"parentHashes":[1164760504],"friendlyName":"private-matches-control","supportsFeedFiltering":false,"display":false,"order":1901,"hash":3024701316,"index":41,"redacted":false,"blacklisted":false},"-1095868816":{"displayProperties":{"description":"Статистика по режиму \"Контроль\" в Горниле.","name":"Контроль","icon":"/common/destiny2_content/icons/DestinyActivityModeDefinition_922ae83203f6134bae00937d12eab3a2.png","hasIcon":true},"pgcrImage":"/img/theme/destiny/bgs/stats/banner_crucible_1.jpg","modeType":10,"activityModeCategory":2,"isTeamBased":true,"tier":0,"isAggregateMode":true,"parentHashes":[1164760504],"friendlyName":"control","supportsFeedFiltering":false,"display":true,"order":1150,"hash":3199098480,"index":16,"redacted":false,"blacklisted":false},"-869856616":{"displayProperties":{"description":"Статистика по заданиям быстрой игры.","name":"Быстрая игра. PvP","icon":"/common/destiny2_content/icons/DestinyActivityModeDefinition_fb3e9149c43f7a2e8f8b66cbea7845fe.png","hasIcon":true},"pgcrImage":"/img/theme/destiny/bgs/stats/banner_crucible_1.jpg","modeType":70,"activityModeCategory":2,"isTeamBased":false,"tier":0,"isAggregateMode":true,"friendlyName":"pvpQuickplay","supportsFeedFiltering":false,"display":true,"order":1000,"hash":3425110680,"index":6,"redacted":false,"blacklisted":false},"-815750908":{"displayProperties":{"description":"Статистика по режиму Железного знамени: \"Столкновение\"","name":"Железное знамя: Столкновение","icon":"/common/destiny2_content/icons/DestinyActivityModeDefinition_fe57052d7cf971f7502daa75a2ca2437.png","hasIcon":true},"pgcrImage":"/img/theme/destiny/bgs/stats/banner_crucible_1.jpg","modeType":44,"activityModeCategory":2,"isTeamBased":true,"tier":0,"isAggregateMode":false,"parentHashes":[1826469369],"friendlyName":"iron-banner-clash","supportsFeedFiltering":false,"display":true,"order":1400,"hash":3479216388,"index":27,"redacted":false,"blacklisted":false},"-797199657":{"displayProperties":{"description":"Статистика по всем ситуациям, когда вы просто гуляете по карте в надежде встретить свою любовь. Я имею в виду патрулирование. Или приключения. Или как там сейчас это называется у молодежи.","name":"Режим исследования","icon":"/common/destiny2_content/icons/DestinyActivityModeDefinition_0aa1d7b0e0ac2c6820036b6b3dde3e5b.png","hasIcon":true},"pgcrImage":"/img/theme/destiny/bgs/stats/banner_patrol_1.jpg","modeType":6,"activityModeCategory":1,"isTeamBased":false,"tier":0,"isAggregateMode":false,"parentHashes":[1164760493],"friendlyName":"patrol","supportsFeedFiltering":false,"display":true,"order":5000,"hash":3497767639,"index":3,"redacted":false,"blacklisted":false},"-621632665":{"displayProperties":{"description":"Статистика по \"Контролю\" в быстрой игре.","name":"Контроль: быстрая игра","icon":"/common/destiny2_content/icons/DestinyActivityModeDefinition_922ae83203f6134bae00937d12eab3a2.png","hasIcon":true},"pgcrImage":"/img/theme/destiny/bgs/stats/banner_crucible_1.jpg","modeType":73,"activityModeCategory":2,"isTeamBased":true,"tier":0,"isAggregateMode":false,"parentHashes":[3199098480],"friendlyName":"controlQuickplay","supportsFeedFiltering":false,"display":true,"order":1150,"hash":3673334631,"index":17,"redacted":false,"blacklisted":false},"-514207857":{"displayProperties":{"description":"Добро пожаловать в закрытые матчи \"Выживание\", где все высосано из пальца, а набор очков лишен смысла.","name":"Закрытые матчи: \"Выживание\"","icon":"/common/destiny2_content/icons/DestinyActivityModeDefinition_fb3e9149c43f7a2e8f8b66cbea7845fe.png","hasIcon":true},"pgcrImage":"/img/theme/destiny/bgs/stats/banner_crucible_1.jpg","modeType":55,"activityModeCategory":2,"isTeamBased":true,"tier":0,"isAggregateMode":false,"parentHashes":[1164760504],"friendlyName":"private-matches-survival","supportsFeedFiltering":false,"display":false,"order":1904,"hash":3780759439,"index":44,"redacted":false,"blacklisted":false},"-505945566":{"displayProperties":{"description":"Сколько раз нас вынесли всей командой в сумрачном налете на той неделе? (Намек: не больше одного раза)","name":"Сумрачные налеты","icon":"/common/destiny2_content/icons/DestinyActivityModeDefinition_234e7e18549d5eae2ddb012f2bcb203a.png","hasIcon":true},"pgcrImage":"/img/theme/destiny/bgs/stats/banner_strikes_1.jpg","modeType":16,"activityModeCategory":1,"isTeamBased":false,"tier":0,"isAggregateMode":false,"parentHashes":[2394616003],"friendlyName":"nightfall","supportsFeedFiltering":false,"display":true,"order":3200,"hash":3789021730,"index":10,"redacted":false,"blacklisted":false},"-473465279":{"displayProperties":{"description":"Матчи \"Напарники\", которые не являются частью Багряных дней.","name":"Напарники","icon":"/common/destiny2_content/icons/DestinyActivityModeDefinition_f9d1438e0536f36e868e691eb0acfc4d.png","hasIcon":true},"pgcrImage":"/img/theme/destiny/bgs/stats/banner_crucible_1.jpg","modeType":50,"activityModeCategory":2,"isTeamBased":true,"tier":0,"isAggregateMode":false,"parentHashes":[1703282980],"friendlyName":"doubles","supportsFeedFiltering":false,"display":true,"order":1377,"hash":3821502017,"index":35,"redacted":false,"blacklisted":false},"-432922534":{"displayProperties":{"description":"Добро пожаловать в закрытые матчи \"Превосходство\", где все высосано из пальца, а набор очков лишен смысла.","name":"Закрытые матчи: \"Превосходство\"","icon":"/common/destiny2_content/icons/DestinyActivityModeDefinition_ca750af7ed2f0ec3c8e2f019c85f7bab.png","hasIcon":true},"pgcrImage":"/img/theme/destiny/bgs/stats/banner_crucible_1.jpg","modeType":53,"activityModeCategory":2,"isTeamBased":true,"tier":0,"isAggregateMode":false,"parentHashes":[1164760504],"friendlyName":"private-matches-supremacy","supportsFeedFiltering":false,"display":false,"order":1903,"hash":3862044762,"index":43,"redacted":false,"blacklisted":false},"-400492470":{"displayProperties":{"description":"Статистика по режиму \"Суд\"","name":"Суд","icon":"/common/destiny2_content/icons/DestinyActivityModeDefinition_e74b3385c5269da226372df8ae7f500d.png","hasIcon":true},"pgcrImage":"/img/destiny_content/pgcr/reckoning.jpg","modeType":76,"activityModeCategory":1,"isTeamBased":false,"tier":0,"isAggregateMode":false,"parentHashes":[1164760493],"friendlyName":"reckoning","supportsFeedFiltering":false,"display":true,"order":5000,"hash":3894474826,"index":54,"redacted":false,"blacklisted":false},"-390342404":{"displayProperties":{"description":"Статистика по режиму \"Спасение\" в Горниле.","name":"Спасение","icon":"/common/destiny2_content/icons/DestinyActivityModeDefinition_fb3e9149c43f7a2e8f8b66cbea7845fe.png","hasIcon":true},"pgcrImage":"/img/theme/destiny/bgs/stats/banner_crucible_1.jpg","modeType":67,"activityModeCategory":2,"isTeamBased":true,"tier":0,"isAggregateMode":false,"parentHashes":[1164760504],"friendlyName":"salvage","supportsFeedFiltering":false,"display":true,"order":1376,"hash":3904624892,"index":22,"redacted":false,"blacklisted":false},"-261966967":{"displayProperties":{"description":"","name":"Рывок","icon":"/common/destiny2_content/icons/DestinyActivityModeDefinition_fb3e9149c43f7a2e8f8b66cbea7845fe.png","hasIcon":true},"pgcrImage":"/img/theme/destiny/bgs/stats/banner_crucible_1.jpg","modeType":65,"activityModeCategory":2,"isTeamBased":true,"tier":0,"isAggregateMode":false,"parentHashes":[1164760504],"friendlyName":"breakthrough","supportsFeedFiltering":false,"display":true,"order":5000,"hash":4033000329,"index":55,"redacted":false,"blacklisted":false},"-242891787":{"displayProperties":{"description":"Статистика по \"Столкновению\" в состязательном режиме.","name":"Столкновение: состязательная игра","icon":"/common/destiny2_content/icons/DestinyActivityModeDefinition_fb3e9149c43f7a2e8f8b66cbea7845fe.png","hasIcon":true},"pgcrImage":"/img/theme/destiny/bgs/stats/banner_crucible_1.jpg","modeType":72,"activityModeCategory":2,"isTeamBased":true,"tier":0,"isAggregateMode":false,"parentHashes":[1585787840],"friendlyName":"clashCompetitive","supportsFeedFiltering":false,"display":true,"order":1100,"hash":4052075509,"index":21,"redacted":false,"blacklisted":false},"-184361721":{"displayProperties":{"description":"Статистика по обычным налетам.","name":"Обычные налеты","icon":"/common/destiny2_content/icons/DestinyActivityModeDefinition_38e26baf417d26bb3548d97bf4872b54.png","hasIcon":true},"pgcrImage":"/img/theme/destiny/bgs/stats/banner_strikes_1.jpg","modeType":3,"activityModeCategory":1,"isTeamBased":false,"tier":0,"isAggregateMode":false,"parentHashes":[2394616003],"friendlyName":"strikes-normal","supportsFeedFiltering":false,"display":true,"order":3000,"hash":4110605575,"index":9,"redacted":false,"blacklisted":false},"-82084646":{"displayProperties":{"description":"Статистика по режиму Железного знамени: \"Превосходство\"","name":"Железное знамя: Превосходство","icon":"/common/destiny2_content/icons/DestinyActivityModeDefinition_fe57052d7cf971f7502daa75a2ca2437.png","hasIcon":true},"pgcrImage":"/img/theme/destiny/bgs/stats/banner_crucible_1.jpg","modeType":45,"activityModeCategory":2,"isTeamBased":true,"tier":0,"isAggregateMode":false,"parentHashes":[1826469369],"friendlyName":"iron-banner-supremacy","supportsFeedFiltering":false,"display":true,"order":1400,"hash":4212882650,"index":26,"redacted":false,"blacklisted":false}}